utility_bill_scraper/__init__.py
utility_bill_scraper/bin/__init__.py
utility_bill_scraper/bin/ubs.py
utility_bill_scraper/canada/on/enbridge.py
utility_bill_scraper/canada/on/kitchener_utilities.py
utility_bill_scraper/canada/on/kitchener_wilmot_hydro.py
utility_bill_scraper/google_drive_helpers.py
utility_bill_scraper-0.10.3.dist-info/entry_points.txt
utility_bill_scraper-0.10.3.dist-info/LICENSE.md
utility_bill_scraper-0.10.3.dist-info/WHEEL
utility_bill_scraper-0.10.3.dist-info/METADATA
utility_bill_scraper-0.10.3.dist-info/RECORD
