Metadata-Version: 2.1
Name: utility-bill-scraper
Version: 0.10.3
Summary: Utility bill scraper for extracting data from pdfs and websites.
License: BSD-3-Clause
Author: Ryan Fobel
Author-email: ryan@fobel.net
Requires-Python: >=3.7.1,<3.11
Classifier: License :: OSI Approved :: BSD License
Classifier: Programming Language :: Python :: 3
Classifier: Programming Language :: Python :: 3.10
Classifier: Programming Language :: Python :: 3.8
Classifier: Programming Language :: Python :: 3.9
Requires-Dist: arrow (>=1.2.0,<2.0.0)
Requires-Dist: beautifulsoup4 (>=4.6.0,<5.0.0)
Requires-Dist: google-api-python-client (>=2.27.0,<3.0.0)
Requires-Dist: matplotlib (>=3.2,<4.0)
Requires-Dist: numpy (>=1.16,<2.0)
Requires-Dist: pandas (>=1.1.0,<2.0.0)
Requires-Dist: pdfminer (>=20191125,<20191126)
Requires-Dist: python-dotenv (>=0.19.1,<0.20.0)
Requires-Dist: selenium (>=3.141.0,<4.0.0)
